[{"studentName":" ABHISHEK B K","studentUSN":" 4CB19IS001","subjects":[{"subjectCode":"18CS644","subjectName":"ADVANCED JAVA AND J2EE","iaMarks":"32","eaMarks":"33","totalMarks":"65","result":"P"},{"subjectCode":"18IS61","subjectName":"FILE STRUCTURES","iaMarks":"35","eaMarks":"46","totalMarks":"81","result":"P"},{"subjectCode":"18ISL67","subjectName":"FILE STRUCTURES LABORATORY WITH MINI PROJECT","iaMarks":"33","eaMarks":"53","totalMarks":"86","result":"P"},{"subjectCode":"18IS62","subjectName":"SOFTWARE TESTING","iaMarks":"30","eaMarks":"48","totalMarks":"78","result":"P"},{"subjectCode":"18ISL66","subjectName":"SOFTWARE TESTING LABORATORY","iaMarks":"38","eaMarks":"53","totalMarks":"91","result":"P"},{"subjectCode":"18ME653","subjectName":"SUPPLY CHAIN MANAGEMENT","iaMarks":"37","eaMarks":"45","totalMarks":"82","result":"P"},{"subjectCode":"18CS63","subjectName":"WEB TECHNOLOGY AND ITS APPLICATIONS","iaMarks":"27","eaMarks":"23","totalMarks":"50","result":"P"}]},{"studentName":" ADITHYA M NAYAK","studentUSN":" 4CB19IS002","subjects":[{"subjectCode":"18CS644","subjectName":"ADVANCED JAVA AND J2EE","iaMarks":"35","eaMarks":"40","totalMarks":"75","result":"P"},{"subjectCode":"18IS61","subjectName":"FILE STRUCTURES","iaMarks":"34","eaMarks":"27","totalMarks":"61","result":"P"},{"subjectCode":"18ISL67","subjectName":"FILE STRUCTURES LABORATORY WITH MINI PROJECT","iaMarks":"33","eaMarks":"47","totalMarks":"80","result":"P"},{"subjectCode":"18IS62","subjectName":"SOFTWARE TESTING","iaMarks":"35","eaMarks":"31","totalMarks":"66","result":"P"},{"subjectCode":"18ISL66","subjectName":"SOFTWARE TESTING LABORATORY","iaMarks":"33","eaMarks":"48","totalMarks":"81","result":"P"},{"subjectCode":"18ME653","subjectName":"SUPPLY CHAIN MANAGEMENT","iaMarks":"37","eaMarks":"40","totalMarks":"77","result":"P"},{"subjectCode":"18CS63","subjectName":"WEB TECHNOLOGY AND ITS APPLICATIONS","iaMarks":"33","eaMarks":"48","totalMarks":"81","result":"P"}]},{"studentName":" ADITHYA M NAYAK","studentUSN":" 4CB19IS002","subjects":[{"subjectCode":"18CS644","subjectName":"ADVANCED JAVA AND J2EE","iaMarks":"35","eaMarks":"40","totalMarks":"75","result":"P"},{"subjectCode":"18IS61","subjectName":"FILE STRUCTURES","iaMarks":"34","eaMarks":"27","totalMarks":"61","result":"P"},{"subjectCode":"18ISL67","subjectName":"FILE STRUCTURES LABORATORY WITH MINI PROJECT","iaMarks":"33","eaMarks":"47","totalMarks":"80","result":"P"},{"subjectCode":"18IS62","subjectName":"SOFTWARE TESTING","iaMarks":"35","eaMarks":"31","totalMarks":"66","result":"P"},{"subjectCode":"18ISL66","subjectName":"SOFTWARE TESTING LABORATORY","iaMarks":"33","eaMarks":"48","totalMarks":"81","result":"P"},{"subjectCode":"18ME653","subjectName":"SUPPLY CHAIN MANAGEMENT","iaMarks":"37","eaMarks":"40","totalMarks":"77","result":"P"},{"subjectCode":"18CS63","subjectName":"WEB TECHNOLOGY AND ITS APPLICATIONS","iaMarks":"33","eaMarks":"48","totalMarks":"81","result":"P"}]},{"studentName":" ANANYA U","studentUSN":" 4CB19IS004","subjects":[{"subjectCode":"18CS644","subjectName":"ADVANCED JAVA AND J2EE","iaMarks":"33","eaMarks":"26","totalMarks":"59","result":"P"},{"subjectCode":"18IS61","subjectName":"FILE STRUCTURES","iaMarks":"34","eaMarks":"35","totalMarks":"69","result":"P"},{"subjectCode":"18ISL67","subjectName":"FILE STRUCTURES LABORATORY WITH MINI PROJECT","iaMarks":"30","eaMarks":"24","totalMarks":"54","result":"P"},{"subjectCode":"18IS62","subjectName":"SOFTWARE TESTING","iaMarks":"32","eaMarks":"39","totalMarks":"71","result":"P"},{"subjectCode":"18ISL66","subjectName":"SOFTWARE TESTING LABORATORY","iaMarks":"29","eaMarks":"50","totalMarks":"79","result":"P"},{"subjectCode":"18ME653","subjectName":"SUPPLY CHAIN MANAGEMENT","iaMarks":"37","eaMarks":"39","totalMarks":"76","result":"P"},{"subjectCode":"18CS63","subjectName":"WEB TECHNOLOGY AND ITS APPLICATIONS","iaMarks":"25","eaMarks":"28","totalMarks":"53","result":"P"}]}]